noos_tf/__init__.py
noos_tf/api.py
noos_tf/cli.py
noos_tf/client.py
noos_tf-0.0.9.dist-info/LICENSE
noos_tf-0.0.9.dist-info/METADATA
noos_tf-0.0.9.dist-info/WHEEL
noos_tf-0.0.9.dist-info/entry_points.txt
noos_tf-0.0.9.dist-info/RECORD
